pypglab/__init__.py
pypglab/const.py
pypglab/device.py
pypglab/entity.py
pypglab/exception.py
pypglab/helper.py
pypglab/mqtt.py
pypglab/relay.py
pypglab/sensor.py
pypglab/shutter.py
pypglab/validation.py
pypglab-0.0.4.dist-info/METADATA
pypglab-0.0.4.dist-info/WHEEL
pypglab-0.0.4.dist-info/licenses/LICENSE
pypglab-0.0.4.dist-info/RECORD
