Metadata-Version: 2.4
Name: pypglab
Version: 0.0.4
Summary: An asynchronous Python library to communicate with PG LAB Electronics devices over MQTT.
Project-URL: Homepage, https://github.com/pglab-electronics/pypglab
Author-email: Pierluigi Garaventa <pglab.electronics@gmail.com>
License: MIT License
License-File: LICENSE
Keywords: pglab, pypglab
Classifier: License :: OSI Approved :: MIT License
Classifier: Operating System :: OS Independent
Classifier: Programming Language :: Python :: 3
Classifier: Topic :: Home Automation
Classifier: Topic :: Software Development :: Libraries :: Python Modules
Requires-Python: >=3.8
Requires-Dist: paho-mqtt
Requires-Dist: voluptuous
